linkml_validator/__init__.py
linkml_validator/cli.py
linkml_validator/models.py
linkml_validator/utils.py
linkml_validator/validator.py
linkml_validator/plugins/__init__.py
linkml_validator/plugins/base.py
linkml_validator/plugins/jsonschema_validation.py
linkml_validator/plugins/range_validation.py
tests/integration/__init__.py
tests/integration/test_custom_plugin.py
tests/integration/test_validator.py
tests/unit/__init__.py
linkml_validator-0.4.5.dist-info/LICENSE
linkml_validator-0.4.5.dist-info/METADATA
linkml_validator-0.4.5.dist-info/WHEEL
linkml_validator-0.4.5.dist-info/entry_points.txt
linkml_validator-0.4.5.dist-info/top_level.txt
linkml_validator-0.4.5.dist-info/RECORD
