Metadata-Version: 2.1
Name: linkml-validator
Version: 0.4.5
Summary: LinkML Validator
Home-page: https://github.com/linkml/linkml-validator
Author: Deepak Unni
Author-email: deepak.unni3@gmail.com
License: BSD3
Platform: UNKNOWN
Classifier: Programming Language :: Python :: 3 :: Only
Classifier: Programming Language :: Python :: 3.8
Classifier: Programming Language :: Python :: 3.9
Classifier: License :: OSI Approved :: BSD License
Classifier: Topic :: Scientific/Engineering :: Bio-Informatics
Classifier: Intended Audience :: Developers
Classifier: Intended Audience :: Science/Research
Classifier: Intended Audience :: Healthcare Industry
Requires-Python: >=3.8
License-File: LICENSE
Requires-Dist: pydantic (>=1.8.2)
Requires-Dist: linkml (>=1.1.18)
Requires-Dist: linkml-runtime (>=1.2.0)
Requires-Dist: stringcase (>=1.2.0)
Requires-Dist: click (>=7.0.0)
Provides-Extra: dev
Requires-Dist: pytest ; extra == 'dev'
Requires-Dist: pytest-cov ; extra == 'dev'
Requires-Dist: mkdocs ; extra == 'dev'
Requires-Dist: mkdocs-material ; extra == 'dev'
Requires-Dist: mkdocstrings ; extra == 'dev'
Requires-Dist: mkdocstrings-python-legacy ; extra == 'dev'
